uniprot_xplorer/__init__.py
uniprot_xplorer/uniprot.py
uniprot_xplorer/uniprot_collection.py
uniprot_xplorer-0.1.1.dist-info/METADATA
uniprot_xplorer-0.1.1.dist-info/WHEEL
uniprot_xplorer-0.1.1.dist-info/top_level.txt
uniprot_xplorer-0.1.1.dist-info/RECORD
