Metadata-Version: 2.1
Name: uniprot_xplorer
Version: 0.1.1
Summary: __init__.py and README.md files updated
Author-email: BALIGAND Elsa <elsa.baligand@etu.univ-lyon1.fr>, EL AOUDATI Salma <salma.el-aoudati@etu.univ-lyon1.fr>
Project-URL: repository, http://pedago-service.univ-lyon1.fr:2325/ebaligand/uniprot.git
Requires-Python: >=3.10
Requires-Dist: matplotlib>=3.9.2
